README
bup-cron
setup.py
bup_cron/__init__.py
bup_cron.egg-info/PKG-INFO
bup_cron.egg-info/SOURCES.txt
bup_cron.egg-info/dependency_links.txt
bup_cron.egg-info/top_level.txt